[
{"word": "abduct", "translated": "uprowadza\u0107", "explanation": "to force someone to go somewhere with you, often using threats or violence", "pronunciation": "/\u00e6b\u02c8d\u028ckt/", "sentence": "The company director was abducted from his car by terrorists.", "media_fname": "abduct.mp3", "type": "verb", "sentence_gap": "The company director was ________ from his car by terrorists.", "gap_term": "abducted", "picture": "", "synonyms": ""},
{"word": "agile", "translated": "zwinny", "explanation": "able to move your body quickly and easily", "pronunciation": "/\u02c8\u00e6d\u0292.\u0259l/", "sentence": "Monkeys are very agile climbers.Monkeys are very agile climbers.", "media_fname": "agile.mp3", "type": "adjective", "sentence_gap": "Monkeys are very _____ climbers.Monkeys are very _____ climbers.", "gap_term": "agile", "picture": "", "synonyms": ""},
{"word": "morsel", "translated": "k\u0105sek", "explanation": "", "pronunciation": "/\u02c8m\u0254\u02d0r.s\u0259l/", "sentence": "The prisoners ate every last morsel.", "media_fname": "morsel.mp3", "type": "noun", "sentence_gap": "The prisoners ate every last ______.", "gap_term": "morsel", "picture": "", "synonyms": ""},
{"word": "onerous", "translated": "uci\u0105\u017cliwy, ci\u0119\u017cki", "explanation": "needing great effort; causing trouble or worry", "pronunciation": "/\u02c8\u0251\u02d0.n\u025a.\u0259s/", "sentence": "She found the duties of motherhood onerous.", "media_fname": "onerous.mp3", "type": "adjective", "sentence_gap": "She found the duties of motherhood _______.", "gap_term": "onerous", "picture": "", "synonyms": ""},
{"word": "outcast", "translated": "wyrzutek", "explanation": "a person who has no place in their society or in a particular group, because the society or group refuses to accept them", "pronunciation": "/\u02c8a\u028at.k\u00e6st/", "sentence": "She has spent her life trying to help the homeless and other social outcasts.", "media_fname": "outcast.mp3", "type": "noun", "sentence_gap": "She has spent her life trying to help the homeless and other social ________.", "gap_term": "outcasts", "picture": "", "synonyms": ""},
{"word": "pancreas", "translated": "trzustka", "explanation": "", "pronunciation": "/\u02c8p\u00e6\u014b.kri.\u0259s/", "sentence": "The part of the pancreas in digestion also is better understood.", "media_fname": "pancreas.mp3", "type": "noun", "sentence_gap": "The part of the ________ in digestion also is better understood.", "gap_term": "pancreas", "picture": "", "synonyms": ""},
{"word": "pasture", "translated": "pastwisko", "explanation": "", "pronunciation": "/\u02c8p\u00e6s.t\u0283\u025a/", "sentence": "The sheep were grazing on the lush green pastures.", "media_fname": "pasture.mp3", "type": "noun", "sentence_gap": "The sheep were grazing on the lush green ________.", "gap_term": "pastures", "picture": "", "synonyms": ""},
{"word": "residual", "translated": "pozosta\u0142y, szcz\u0105tkowy", "explanation": "remaining after most of something has gone", "pronunciation": "/r\u026a\u02c8z\u026ad\u0292.ju.\u0259l/", "sentence": "I still felt some residual bitterness ten years after my divorce.", "media_fname": "residual.mp3", "type": "adjective", "sentence_gap": "I still felt some ________ bitterness ten years after my divorce.", "gap_term": "residual", "picture": "", "synonyms": ""},
{"word": "rooster", "translated": "kogut", "explanation": "", "pronunciation": "/\u02c8ru\u02d0.st\u025a/", "sentence": "I heard a rooster crow.", "media_fname": "rooster.mp3", "type": "noun", "sentence_gap": "I heard a _______ crow.", "gap_term": "rooster", "picture": "", "synonyms": ""},
{"word": "tenant", "translated": "najemca, lokator", "explanation": "a person who pays rent for the use of land or a building", "pronunciation": "/\u02c8ten.\u0259nt/", "sentence": "He was cruel to his tenants.", "media_fname": "tenant.mp3", "type": "noun", "sentence_gap": "He was cruel to his _______.", "gap_term": "tenants", "picture": "", "synonyms": ""},
{"word": "trample", "translated": "depta\u0107", "explanation": "", "pronunciation": "/\u02c8tr\u00e6m.p\u0259l/", "sentence": "She shouted at the boys for trampling on her flowers.", "media_fname": "trample.mp3", "type": "verb", "sentence_gap": "She shouted at the boys for _________ on her flowers.", "gap_term": "trampling", "picture": "", "synonyms": ""},
{"word": "underhand", "translated": "nieuczciwy, skryty", "explanation": "done secretly, and sometimes dishonestly, in order to achieve an advantage", "pronunciation": "/\u02cc\u028cn.d\u025a\u02c8h\u00e6nd/", "sentence": "What really angered her was the dirty, underhand way they had tricked her.", "media_fname": "underhand.mp3", "type": "adjective", "sentence_gap": "What really angered her was the dirty, _________ way they had tricked her.", "gap_term": "underhand", "picture": "", "synonyms": ""},
{"word": "unfathomable", "translated": "niezg\u0142\u0119biony", "explanation": "impossible to understand", "pronunciation": "/\u028cn\u02c8f\u00e6\u00f0.\u0259.m\u0259.b\u0259l/", "sentence": "For some unfathomable reason they built the toilet next to the kitchen.", "media_fname": "unfathomable.mp3", "type": "adjective", "sentence_gap": "For some ____________ reason they built the toilet next to the kitchen.", "gap_term": "unfathomable", "picture": "", "synonyms": ""},
{"word": "viaduct", "translated": "wiadukt", "explanation": "", "pronunciation": "/\u02c8va\u026a\u0259.d\u028ckt/", "sentence": "An ancient Roman viaduct crosses the valley.", "media_fname": "viaduct.mp3", "type": "noun", "sentence_gap": "An ancient Roman _______ crosses the valley.", "gap_term": "viaduct", "picture": "", "synonyms": ""},
{"word": "vindictive", "translated": "m\u015bciwy", "explanation": "having or showing a wish to harm someone because you think that they harmed you; unwilling to forgive", "pronunciation": "/v\u026an\u02c8d\u026ak.t\u026av/", "sentence": "He accused her of being vindictive.", "media_fname": "vindictive.mp3", "type": "adjective", "sentence_gap": "He accused her of being __________.", "gap_term": "vindictive", "picture": "", "synonyms": ""}
]